[
    {
        "type": "convention",
        "module": "fetch_http_status_code",
        "obj": "",
        "line": 21,
        "column": 0,
        "endLine": null,
        "endColumn": null,
        "path": "/Users/manishsingh/Desktop/Mini Project /automated-code-review/data/raw/python-mini-projects/projects/Fetch HTTP status code/fetch_http_status_code.py",
        "symbol": "line-too-long",
        "message": "Line too long (107/100)",
        "message-id": "C0301"
    },
    {
        "type": "error",
        "module": "fetch_http_status_code",
        "obj": "",
        "line": 4,
        "column": 0,
        "endLine": 4,
        "endColumn": 12,
        "path": "/Users/manishsingh/Desktop/Mini Project /automated-code-review/data/raw/python-mini-projects/projects/Fetch HTTP status code/fetch_http_status_code.py",
        "symbol": "import-error",
        "message": "Unable to import 'emoji'",
        "message-id": "E0401"
    },
    {
        "type": "convention",
        "module": "fetch_http_status_code",
        "obj": "",
        "line": 21,
        "column": 23,
        "endLine": 21,
        "endColumn": 47,
        "path": "/Users/manishsingh/Desktop/Mini Project /automated-code-review/data/raw/python-mini-projects/projects/Fetch HTTP status code/fetch_http_status_code.py",
        "symbol": "use-maxsplit-arg",
        "message": "Use str(e.reason).split(']', maxsplit=1)[0] instead",
        "message-id": "C0207"
    },
    {
        "type": "refactor",
        "module": "fetch_http_status_code",
        "obj": "",
        "line": 11,
        "column": 15,
        "endLine": 11,
        "endColumn": 34,
        "path": "/Users/manishsingh/Desktop/Mini Project /automated-code-review/data/raw/python-mini-projects/projects/Fetch HTTP status code/fetch_http_status_code.py",
        "symbol": "consider-using-with",
        "message": "Consider using 'with' for resource-allocating operations",
        "message-id": "R1732"
    }
]